LICENSE
README.md
pyproject.toml
setup.cfg
setup.py
serverjars/__init__.py
serverjars/constants.py
serverjars/exception.py
serverjars/modded.py
serverjars/py.typed
serverjars/vanilla.py
serverjars_api.egg-info/PKG-INFO
serverjars_api.egg-info/SOURCES.txt
serverjars_api.egg-info/dependency_links.txt
serverjars_api.egg-info/not-zip-safe
serverjars_api.egg-info/requires.txt
serverjars_api.egg-info/top_level.txt