Metadata-Version: 2.1
Name: serverjars-api
Version: 1.4.0
Summary: Download and fetch details about Minecraft server jars.
Home-page: https://github.com/legopitstop/serverjars-py/
Author: Legopitstop
Author-email: contact@lpsmods.dev
License: MIT
Project-URL: Download, https://github.com/legopitstop/serverjars-py/releases
Project-URL: Documentation, https://docs.lpsmods.dev/serverjars-api
Project-URL: Source Code, https://github.com/legopitstop/serverjars-py
Keywords: ServerJars,Minecraft,Servers,Bedrock,API
Classifier: Development Status :: 5 - Production/Stable
Classifier: Intended Audience :: Developers
Classifier: License :: OSI Approved :: MIT License
Classifier: Programming Language :: Python :: 3.11
Requires-Python: >=3.8
Provides-Extra: testing
License-File: LICENSE
